Metadata-Version: 2.1
Name: HPC-submission-tools
Version: 1.8
Summary: Tools pertaining to use of HPC clusters with slurm file systems
Home-page: https://github.com/RossJamesUrquhart/HPC_submission_tools
Download-URL: https://github.com/RossJamesUrquhart/HPC_submission_tools/archive/refs/tags/v1.8.tar.gz
Author: Ross Urquhart
Author-email: ross.urquhart@strath.ac.uk
License: MIT
Keywords: HPC,Command line
Classifier: Development Status :: 3 - Alpha
Classifier: Intended Audience :: Developers
Classifier: Topic :: Software Development :: Build Tools
Classifier: License :: OSI Approved :: MIT License
Classifier: Programming Language :: Python :: 3.9
Classifier: Programming Language :: Python :: 3.8
Classifier: Programming Language :: Python :: 3.7
Classifier: Programming Language :: Python :: 3.6
Classifier: Programming Language :: Python :: 3.5
Classifier: Programming Language :: Python :: 3
Classifier: Programming Language :: Python :: 3.4
License-File: LICENSE.txt
